{
  "pre_survey_en": {
    "description": "Pre Survey bot",
    "locale": "en-US",
    "process_behavior": "BUILD",
    "child_directed": true,
    "idle_session_ttl_in_seconds": "600",
    "abort_statement": {
      "content": "Sorry, I am not able to assist at this time.",
      "content_type": "PlainText"
    },
    "clarification_prompt": {
      "max_attempts": 2,
      "content": "Sorry, I didn't understand that. Please try again.",
      "content_type": "PlainText"
    },
    "slot_types": {
      "YesNo": {
        "description": "Custom slot for Yes-No kind of questions",
        "value_selection_strategy": "TOP_RESOLUTION",
        "values": {
          "Yes": {
            "synonyms": [
              "y",
              "yes",
              "yep",
              "yeah",
              "yup",
              "ya",
              "yah"
            ]
          },
          "No": {
            "synonyms": [
              "n",
              "no",
              "nope",
              "nah",
              "not"
            ]
          }
        }
      },
      "Age": {
        "description": "Age of caller",
        "value_selection_strategy": "TOP_RESOLUTION",
        "values": {
          "0": {
            "synonyms": [
              "zero",
              "none"
            ]
          },
          "1": {
            "synonyms": [
              "one"
            ]
          },
          "2": {
            "synonyms": [
              "two"
            ]
          },
          "3": {
            "synonyms": [
              "three"
            ]
          },
          "4": {
            "synonyms": [
              "four"
            ]
          },
          "5": {
            "synonyms": [
              "five"
            ]
          },
          "6": {
            "synonyms": [
              "six"
            ]
          },
          "7": {
            "synonyms": [
              "seven"
            ]
          },
          "8": {
            "synonyms": [
              "eight"
            ]
          },
          "9": {
            "synonyms": [
              "nine"
            ]
          },
          "10": {
            "synonyms": [
              "ten"
            ]
          },
          "11": {
            "synonyms": [
              "eleven"
            ]
          },
          "12": {
            "synonyms": [
              "twelve"
            ]
          },
          "13": {
            "synonyms": [
              "thirteen"
            ]
          },
          "14": {
            "synonyms": [
              "fourteen"
            ]
          },
          "15": {
            "synonyms": [
              "fifteen"
            ]
          },
          "16": {
            "synonyms": [
              "sixteen"
            ]
          },
          "17": {
            "synonyms": [
              "seventeen"
            ]
          },
          "18": {
            "synonyms": [
              "eighteen"
            ]
          },
          "19": {
            "synonyms": [
              "nineteen"
            ]
          },
          "20": {
            "synonyms": [
              "twenty"
            ]
          },
          "21": {
            "synonyms": [
              "twenty one"
            ]
          },
          "Above 21": {
            "synonyms": [
              "22", "23", "24", "25", "26", "27", "28", "29", "30", "31",
              "32", "33", "34", "35", "36", "37", "38", "39", "40", "41",
              "42", "43", "44", "45", "46", "47", "48", "49", "50", "51",
              "52", "53", "54", "55", "56", "57", "58", "59", "60", "61",
              "62", "63", "64", "65", "66", "67", "68", "69", "70", "71",
              "72", "73", "74", "75", "76", "77", "78", "79", "80", "81",
              "82", "83", "84", "85", "86", "87", "88", "89", "90", "91",
              "92", "93", "94", "95", "96", "97", "98", "99", "100", "101",
              "102", "103", "104", "105", "106", "107", "108", "109", "110"
            ]
          },
          "X": {
            "synonyms": [
              "x"
            ]
          },
          "prefer not to answer": {
            "synonyms": ["prefer not", "not answer", "not answering", "not answering"]
          }
        }
      },
      "Gender": {
        "description": "Gender of caller",
        "value_selection_strategy": "TOP_RESOLUTION",
        "values": {
          "boy": {
            "synonyms": [
              "m", "dude", "guy", "man", "he", "male"
            ]
          },
          "girl": {
            "synonyms": ["f", "she", "female", "lady", "woman"]
          },
          "non-binary": {
            "synonyms": ["none", "nonbinary", "non binary"]
          },
          "unknown": {
            "synonyms": ["not sure", "unsure", "x"]
          },
          "prefer not to answer": {
            "synonyms": ["prefer not", "not answer", "not answering"]
          }
        }
      }
    },
    "intents": {
      "Survey": {
        "description": "Survey intent",
        "sample_utterances": [
          "H",
          "Hi",
          "Hello",
          "Help",
          "I need help",
          "Pls",
          "Please",
          "Life",
          "Not safe",
          "Kill",
          "Hurt",
          "Me",
          "Incoming webchat contact"
        ],
        "fulfillment_activity": {
          "type": "ReturnIntent"
        },
        "conclusion_statement": {
          "content": "We'll transfer you now. Please hold for a counsellor.",
          "content_type": "PlainText"
        },
        "rejection_statement": {
          "content": "Sorry, I am not able to assist at this time.",
          "content_type": "PlainText"
        },
        "slots": {
          "aboutSelf": {
            "priority": 1,
            "description": "Caller is calling for self or someone else",
            "slot_constraint": "Required",
            "slot_type": "YesNo",
            "value_elicitation_prompt": {
              "max_attempts": 2,
              "content": "Are you calling about yourself? Please answer Yes or No.",
              "content_type": "PlainText"
            }
          },
          "age": {
            "priority": 2,
            "description": "Age of caller",
            "slot_constraint": "Required",
            "slot_type": "Age",
            "value_elicitation_prompt": {
              "max_attempts": 2,
              "content": "How old are you?",
              "content_type": "PlainText"
            }
          },
          "gender": {
            "priority": 3,
            "description": "Caller's gender",
            "slot_constraint": "Required",
            "slot_type": "Gender",
            "value_elicitation_prompt": {
              "max_attempts": 2,
              "content": "What is your gender?",
              "content_type": "PlainText"
            }
          }
        }
      }
    }
  }
}