{
  "contact": {
    "callerInformation": {},
    "childInformation": {},
    "caseInformation": {
      "splitFormAt": 1
    }
  },
  "case": {
    "sectionTypes": {
      "riskToSelf": {
        "splitFormAt": 13,
        "caseHomeOrder": 1,
        "printOrder": 1,
        "previewFields": [
          "personAtRisk"
        ],
        "layout": {
          "personAtRisk": {
            "widthRatio": 1,
            "labelValueCode": "Case-SectionList-Value/reportAddedAtRisk",
            "includeLabel": false

          }
        }
      },
      "riskFromOthers": {
        "splitFormAt": 9,
        "caseHomeOrder": 2,
        "printOrder": 2,
        "previewFields": [
          "personAtRisk"
        ],
        "layout": {
          "personAtRisk": {
            "widthRatio": 1,
            "labelValueCode": "Case-SectionList-Value/reportAddedAtRisk",
            "includeLabel": false
          }
        }
      },
      "riskToOthers": {
        "previewFields": [
          "whoPresentsRisk"
        ],
        "layout": {
          "whoPresentsRisk": {
           "widthRatio": 1,
            "labelValueCode": "Case-SectionList-Value/reportAddedPresentsRisk",
            "includeLabel": false
          }
        },
        "splitFormAt": 6,
        "caseHomeOrder": 3,
        "printOrder": 3
      },
      "externalIntervention": {
        "previewFields": [
          "referredTo"
        ],
        "splitFormAt": 3,
        "printOrder": 4,        
        "caseHomeLocation": "timeline"
      },
      "document": {
        "splitFormAt": 1,
        "caseHomeOrder": 4,
        "printFormat": "hidden",
        "previewFields": [
          "createdAt",
          "fileName",
          "comments"
        ],
        "layout": {
          "createdAt": {
            "labelTemplateCode": "Case-DocumentFileName",
            "format": "date"
          },
          "fileName": {
            "labelTemplateCode": "Case-DocumentDate",
            "format": "file",
            "widthRatio": 2
          },
          "comments": {
            "labelTemplateCode": "Case-DocumentComments",
            "widthRatio": 2
          }
        }
      },
      "note": {
        "printOrder": 5,
        "caseHomeLocation": "timeline",
        "printFormat": "list",
        "previewFields": ["note"],
        "layout": {
          "note": {}
        }
      }
    }
  }
}
