{
    "attributes": {
        "contacts_waiting_channels": [
            "voice",
            "web",
            "whatsapp",
            "facebook",
            "twitter",
            "instagram",
            "line"
        ],
        "definitionVersion": "mt-v1",
        "feature_flags": {
            "enable_aselo_messaging_ui": true,
            "enable_conferencing": false,
            "enable_counselor_toolkits": true,
            "enable_csam_clc_report": false,
            "enable_fullstory_monitoring": true,
            "enable_lex": true,
            "enable_post_survey": false,
            "enable_save_insights": true,
            "enable_transcripts": false,
            "enable_voice_recordings": false,
            "post_survey_serverless_handled": false
        },
        "permissionConfig": "mt",
        "resources_base_url": ""
    },
    "ui_attributes": {
        "colorTheme": {
            "baseName": "GreyLight",
            "overrides": {
                "MainHeader": {
                    "Button": {
                        "color": "#000000"
                    },
                    "Container": {
                        "background": "#FFFFFF",
                        "color": "#000000"
                    },
                    "Icon": {
                        "color": "#000000"
                    }
                },
                "SideNav": {
                    "Button": {
                        "background": "#FFFFFF"
                    },
                    "Container": {
                        "background": "#FFFFFF"
                    },
                    "Icon": {
                        "color": "#000000"
                    }
                }
            },
            "preset": {
                "id": "mono-light",
                "name": "Simple Light"
            }
        },
        "theme": null
    }
}
